vulnman_default_templates/__init__.py
vulnman_default_templates/locale/__init__.py
vulnman_default_templates/report_templates/__init__.py
vulnman_default_templates/report_templates/default_template/__init__.py
vulnman_default_templates/report_templates/default_template/advisory.py
vulnman_default_templates/report_templates/default_template/apps.py
vulnman_default_templates/report_templates/default_template/csv.py
vulnman_default_templates/report_templates/default_template/pentest_report.py
vulnman_default_templates/report_templates/default_template/vulnerability_report.py
vulnman_default_templates/report_templates/default_template/charts/__init__.py
vulnman_default_templates/report_templates/default_template/charts/donut.py
vulnman_default_templates/report_templates/default_template/charts/polar.py
vulnman_default_templates/report_templates/default_template/templatetags/__init__.py
vulnman_default_templates/report_templates/default_template/templatetags/report_generator.py
vulnman_default_templates/templates/report_templates/default/advisory.md
vulnman_default_templates/templates/report_templates/default/exported_vulnerability.html
vulnman_default_templates/templates/report_templates/default/report.html
vulnman_default_templates/templates/report_templates/default/css/codehilite.css
vulnman_default_templates/templates/report_templates/default/css/fontawesome.min.css
vulnman_default_templates/templates/report_templates/default/fonts/firasans-bold.otf
vulnman_default_templates/templates/report_templates/default/fonts/firasans-italic.otf
vulnman_default_templates/templates/report_templates/default/fonts/firasans-light.otf
vulnman_default_templates/templates/report_templates/default/fonts/firasans-lightitalic.otf
vulnman_default_templates/templates/report_templates/default/fonts/firasans-regular.otf
vulnman_default_templates/templates/report_templates/default/images/cover.png
vulnman_default_templates/templates/report_templates/default/images/draft.png
vulnman_default_templates-0.1.1.dist-info/METADATA
vulnman_default_templates-0.1.1.dist-info/WHEEL
vulnman_default_templates-0.1.1.dist-info/top_level.txt
vulnman_default_templates-0.1.1.dist-info/RECORD
