Metadata-Version: 2.1
Name: vulnman-default-templates
Version: 0.1.1
Summary: Default vulnman templates
Home-page: 
Author: user
Author-email: 
